pythonKdb-3.0.6.data/data/CHANGELOG.txt
pythonKdb-3.0.6.data/data/LICENSE
pythonKdb-3.0.6.data/data/README.rst
pythonKdb-3.0.6.data/data/requirements.txt
qpython/__init__.py
qpython/_pandas.py
qpython/fastutils.cp310-win_amd64.pyd
qpython/fastutils.pyx
qpython/qcollection.py
qpython/qconnection.py
qpython/qreader.py
qpython/qtemporal.py
qpython/qtype.py
qpython/qwriter.py
qpython/utils.py
pythonKdb-3.0.6.dist-info/LICENSE
pythonKdb-3.0.6.dist-info/METADATA
pythonKdb-3.0.6.dist-info/WHEEL
pythonKdb-3.0.6.dist-info/top_level.txt
pythonKdb-3.0.6.dist-info/RECORD
